story_protocol_python_sdk/__init__.py
story_protocol_python_sdk/py.typed
story_protocol_python_sdk/story_client.py
story_protocol_python_sdk/abi/__init__.py
story_protocol_python_sdk/abi/AccessController/AccessController_client.py
story_protocol_python_sdk/abi/ArbitrationPolicyUMA/ArbitrationPolicyUMA_client.py
story_protocol_python_sdk/abi/CoreMetadataModule/CoreMetadataModule_client.py
story_protocol_python_sdk/abi/CoreMetadataViewModule/CoreMetadataViewModule_client.py
story_protocol_python_sdk/abi/DerivativeWorkflows/DerivativeWorkflows_client.py
story_protocol_python_sdk/abi/DisputeModule/DisputeModule_client.py
story_protocol_python_sdk/abi/GroupingModule/GroupingModule_client.py
story_protocol_python_sdk/abi/GroupingWorkflows/GroupingWorkflows_client.py
story_protocol_python_sdk/abi/IPAccountImpl/IPAccountImpl_client.py
story_protocol_python_sdk/abi/IPAssetRegistry/IPAssetRegistry_client.py
story_protocol_python_sdk/abi/IpRoyaltyVaultImpl/IpRoyaltyVaultImpl_client.py
story_protocol_python_sdk/abi/LicenseAttachmentWorkflows/LicenseAttachmentWorkflows_client.py
story_protocol_python_sdk/abi/LicenseRegistry/LicenseRegistry_client.py
story_protocol_python_sdk/abi/LicenseToken/LicenseToken_client.py
story_protocol_python_sdk/abi/LicensingModule/LicensingModule_client.py
story_protocol_python_sdk/abi/MockERC20/MockERC20_client.py
story_protocol_python_sdk/abi/ModuleRegistry/ModuleRegistry_client.py
story_protocol_python_sdk/abi/Multicall3/Multicall3_client.py
story_protocol_python_sdk/abi/PILicenseTemplate/PILicenseTemplate_client.py
story_protocol_python_sdk/abi/RegistrationWorkflows/RegistrationWorkflows_client.py
story_protocol_python_sdk/abi/RoyaltyModule/RoyaltyModule_client.py
story_protocol_python_sdk/abi/RoyaltyPolicyLAP/RoyaltyPolicyLAP_client.py
story_protocol_python_sdk/abi/RoyaltyPolicyLRP/RoyaltyPolicyLRP_client.py
story_protocol_python_sdk/abi/RoyaltyTokenDistributionWorkflows/RoyaltyTokenDistributionWorkflows_client.py
story_protocol_python_sdk-0.3.17.dist-info/licenses/LICENSE
story_protocol_python_sdk-0.3.17.dist-info/METADATA
story_protocol_python_sdk-0.3.17.dist-info/WHEEL
story_protocol_python_sdk-0.3.17.dist-info/top_level.txt
story_protocol_python_sdk-0.3.17.dist-info/RECORD
