Metadata-Version: 2.4
Name: story_protocol_python_sdk
Version: 0.3.17
Summary: A Python SDK for interacting with Story.
Home-page: https://github.com/storyprotocol/python-sdk
Author: Andrew Chung
Author-email: andrew@storyprotocol.xyz
License: MIT
Classifier: Programming Language :: Python :: 3
Classifier: License :: OSI Approved :: MIT License
Classifier: Operating System :: OS Independent
Requires-Python: >=3.10
License-File: LICENSE
Requires-Dist: web3>=7.0.0
Requires-Dist: pytest
Requires-Dist: python-dotenv
Requires-Dist: base58
Provides-Extra: dev
Requires-Dist: pytest; extra == "dev"
Requires-Dist: pytest-cov; extra == "dev"
Requires-Dist: black; extra == "dev"
Requires-Dist: isort; extra == "dev"
Requires-Dist: ruff; extra == "dev"
Requires-Dist: pre-commit; extra == "dev"
Requires-Dist: coverage; extra == "dev"
Requires-Dist: pytest-html; extra == "dev"
Dynamic: author
Dynamic: author-email
Dynamic: classifier
Dynamic: description
Dynamic: description-content-type
Dynamic: home-page
Dynamic: license
Dynamic: license-file
Dynamic: provides-extra
Dynamic: requires-dist
Dynamic: requires-python
Dynamic: summary
